zeroize-1.1.2.dist-info/METADATA
zeroize-1.1.2.dist-info/WHEEL
zeroize-1.1.2.dist-info/license_files/LICENSE-Apache-2.0
zeroize-1.1.2.dist-info/license_files/LICENSE-MIT
zeroize/__init__.py
zeroize/__init__.pyi
zeroize/py.typed
zeroize/zeroize.cp312-win_amd64.pyd
zeroize-1.1.2.dist-info/RECORD
