Metadata-Version: 2.3
Name: zeroize
Version: 1.1.2
Classifier: Development Status :: 4 - Beta
Classifier: Topic :: Security
Classifier: Programming Language :: Rust
Classifier: Programming Language :: Python :: Implementation :: CPython
Classifier: Programming Language :: Python :: Implementation :: PyPy
Classifier: Programming Language :: Python
Classifier: Operating System :: POSIX :: Linux
Classifier: Operating System :: MacOS :: MacOS X
Classifier: Operating System :: Microsoft :: Windows
Classifier: Intended Audience :: Developers
Classifier: Intended Audience :: Education
Classifier: Intended Audience :: Information Technology
Classifier: Intended Audience :: Science/Research
Classifier: Topic :: Education
Classifier: Topic :: Software Development :: Libraries
Classifier: License :: OSI Approved :: Apache Software License
Classifier: License :: OSI Approved :: MIT License
License-File: LICENSE-Apache-2.0
License-File: LICENSE-MIT
Summary: Securely clear secrets from memory. Built on stable Rust primitives which guarantee memory is zeroed using an operation will not be 'optimized away' by the compiler.
Keywords: memory,volatile,secure,memset,zero
Home-Page: https://radumarias.github.io/zeroize-python
Author: Radu Marias <radumarias@gmail.com>
Author-email: Radu Marias <radumarias@gmail.com>
License: Apache-2.0 OR MIT
Requires-Python: >=3.7
Project-URL: Homepage, https://github.com/radumarias/zeroize-python
Project-URL: Issues, https://github.com/radumarias/zeroize-python/issues
